GitFeed-0.1.9.dist-info/DESCRIPTION.rst
GitFeed-0.1.9.dist-info/METADATA
GitFeed-0.1.9.dist-info/RECORD
GitFeed-0.1.9.dist-info/WHEEL
GitFeed-0.1.9.dist-info/entry_points.txt
GitFeed-0.1.9.dist-info/metadata.json
GitFeed-0.1.9.dist-info/top_level.txt
gitfeed/__init__.py
gitfeed/gitfeed.py
