Metadata-Version: 2.0
Name: GitFeed
Version: 0.1.9
Summary: Check your GitHub Newsfeed via the command-line.
Home-page: https://www.github.com/ritiek/GitFeed
Author: Ritiek Malhotra
Author-email: ritiekmalhotra123@gmail.com
License: MIT
Download-URL: https://github.com/Ritiek/GitFeed/archive/v0.1.9.tar.gz
Keywords: GitHub,news,feed,command-line,python
Platform: UNKNOWN
Requires-Dist: colorama (>=0.3.7)
Requires-Dist: requests (>=2.17.3)
